MANIFEST.in
README.rst
setup.py
metzoo_opc/__init__.py
metzoo_opc/metzoo_opc.py
metzoo_opc.egg-info/PKG-INFO
metzoo_opc.egg-info/SOURCES.txt
metzoo_opc.egg-info/dependency_links.txt
metzoo_opc.egg-info/not-zip-safe
metzoo_opc.egg-info/requires.txt
metzoo_opc.egg-info/top_level.txt
test/test.py