Metadata-Version: 1.1
Name: metzoo-opc
Version: 0.1.0
Summary: OPC SDK for Metzoo
Home-page: https://bitbucket.org/edrans/metzoo-sdk/opc
Author: Edrans
Author-email: info@edrans.com
License: MIT
Keywords: metzoo monitoring metric
Platform: UNKNOWN
Classifier: Development Status :: 3 - Alpha
Classifier: License :: OSI Approved :: MIT License
Classifier: Programming Language :: Python :: 2.7
Classifier: Topic :: Text Processing :: Linguistic
